webscraping_tools/__init__.py
webscraping_tools/crypto_scrape_long.py
webscraping_tools/crypto_scrape_simple.py
webscraping_tools/ezScrape.py
webscraping_tools/webscraperHelper.py
webscraping_tools/webscrapingTools.py
webscraping_tools/webscrapingtoolsexample.py
webscraping_tools-0.1.2.dist-info/AUTHORS.rst
webscraping_tools-0.1.2.dist-info/LICENSE
webscraping_tools-0.1.2.dist-info/METADATA
webscraping_tools-0.1.2.dist-info/WHEEL
webscraping_tools-0.1.2.dist-info/top_level.txt
webscraping_tools-0.1.2.dist-info/RECORD
