Metadata-Version: 2.1
Name: webscraping-tools
Version: 0.1.2
Summary: Tools to make webscraping easier.
Home-page: https://github.com/Jack-Tilley/webscraping-tools
Author: Jack Tilley
Author-email: tilley.e.jack@gmail.com
License: MIT license
Keywords: webscraping_tools
Platform: UNKNOWN
Classifier: Development Status :: 2 - Pre-Alpha
Classifier: Intended Audience :: Developers
Classifier: License :: OSI Approved :: MIT License
Classifier: Natural Language :: English
Classifier: Programming Language :: Python :: 2
Classifier: Programming Language :: Python :: 2.7
Classifier: Programming Language :: Python :: 3
Classifier: Programming Language :: Python :: 3.5
Classifier: Programming Language :: Python :: 3.6
Classifier: Programming Language :: Python :: 3.7
Classifier: Programming Language :: Python :: 3.8
Requires-Python: >=2.7, !=3.0.*, !=3.1.*, !=3.2.*, !=3.3.*, !=3.4.*
Requires-Dist: beautifulsoup4
Requires-Dist: selenium
Requires-Dist: requests
